odoo/addons/ssi_accountant_general_audit/README.rst
odoo/addons/ssi_accountant_general_audit/__init__.py
odoo/addons/ssi_accountant_general_audit/__manifest__.py
odoo/addons/ssi_accountant_general_audit/menu.xml
odoo/addons/ssi_accountant_general_audit/data/accountant_client_account_group_data.xml
odoo/addons/ssi_accountant_general_audit/data/accountant_client_account_type_data.xml
odoo/addons/ssi_accountant_general_audit/data/accountant_general_audit_worksheet_type_category_data.xml
odoo/addons/ssi_accountant_general_audit/data/accountant_trial_balance_computation_item_data.xml
odoo/addons/ssi_accountant_general_audit/data/approval_template_data.xml
odoo/addons/ssi_accountant_general_audit/data/ir_sequence_data.xml
odoo/addons/ssi_accountant_general_audit/data/policy_template_data.xml
odoo/addons/ssi_accountant_general_audit/data/sequence_template_accountant_general_report_data.xml
odoo/addons/ssi_accountant_general_audit/demo/accountant_client_account_demo.xml
odoo/addons/ssi_accountant_general_audit/demo/accountant_client_account_type_set_demo.xml
odoo/addons/ssi_accountant_general_audit/demo/accountant_financial_accounting_standard_demo.xml
odoo/addons/ssi_accountant_general_audit/models/__init__.py
odoo/addons/ssi_accountant_general_audit/models/accountant_audit_standard.py
odoo/addons/ssi_accountant_general_audit/models/accountant_audit_standard_item.py
odoo/addons/ssi_accountant_general_audit/models/accountant_client_account.py
odoo/addons/ssi_accountant_general_audit/models/accountant_client_account_group.py
odoo/addons/ssi_accountant_general_audit/models/accountant_client_account_type.py
odoo/addons/ssi_accountant_general_audit/models/accountant_client_account_type_computation_item.py
odoo/addons/ssi_accountant_general_audit/models/accountant_client_account_type_set.py
odoo/addons/ssi_accountant_general_audit/models/accountant_client_adjustment_entry.py
odoo/addons/ssi_accountant_general_audit/models/accountant_client_adjustment_entry_detail.py
odoo14_addon_ssi_accountant_general_audit-14.0.2.2.2.dev1.dist-info/METADATA
odoo14_addon_ssi_accountant_general_audit-14.0.2.2.2.dev1.dist-info/WHEEL
odoo14_addon_ssi_accountant_general_audit-14.0.2.2.2.dev1.dist-info/top_level.txt
odoo14_addon_ssi_accountant_general_audit-14.0.2.2.2.dev1.dist-info/RECORD
